dysql/__init__.py
dysql/annotations.py
dysql/connections.py
dysql/databases.py
dysql/exceptions.py
dysql/mappers.py
dysql/multitenancy.py
dysql/pydantic_mappers.py
dysql/query_utils.py
dysql/test_managers.py
dy_sql-3.2.184.dist-info/WHEEL
dy_sql-3.2.184.dist-info/METADATA
dy_sql-3.2.184.dist-info/RECORD
