Metadata-Version: 2.3
Name: dy-sql
Version: 3.2.184
Summary: Dynamically runs SQL queries and executions.
Author: Adobe
Author-email: Adobe <noreply@adobe.com>
License: MIT
Requires-Dist: sqlalchemy<2
Requires-Dist: pydantic>=2
Requires-Python: >=3.9
Project-URL: Homepage, https://github.com/adobe/dy-sql
